sint/__init__.py
sint/_modidx.py
sint/cons.py
sint/errs.py
sint/guard.py
sint/pttn.py
sint/sign.py
sint/sint.py
sint/tmpl.py
sint/types.py
sint/utils.py
sint-0.0.10.dist-info/LICENSE
sint-0.0.10.dist-info/METADATA
sint-0.0.10.dist-info/WHEEL
sint-0.0.10.dist-info/entry_points.txt
sint-0.0.10.dist-info/top_level.txt
sint-0.0.10.dist-info/RECORD
