Metadata-Version: 2.1
Name: sint
Version: 0.0.10
Summary: si type metric
Home-page: https://github.com/dsm-72/sint
Author: dsm-72
Author-email: sumner.magruder@yale.edu
License: Apache Software License 2.0
Keywords: python int sint signal sign intger str num number
Classifier: Development Status :: 4 - Beta
Classifier: Intended Audience :: Developers
Classifier: Natural Language :: English
Classifier: Programming Language :: Python :: 3.11
Classifier: License :: OSI Approved :: Apache Software License
Requires-Python: >=3.11
License-File: LICENSE
Requires-Dist: ptyp
Requires-Dist: atyp
Requires-Dist: ltyp
Requires-Dist: chck
Requires-Dist: bflag
Provides-Extra: dev
